{
  "description": null,
  "display_name": null,
  "distribution": "contrib",
  "ecosystem": "collector",
  "id": "contrib-extension-otlpencodingextension",
  "name": "otlpencodingextension",
  "repository": "opentelemetry-collector-contrib",
  "status": {
    "class": "extension",
    "codeowners": {
      "active": [
        "dao-jun",
        "VihasMakwana"
      ]
    },
    "distributions": [
      "contrib"
    ],
    "stability": {
      "beta": [
        "extension"
      ]
    }
  },
  "type": "extension"
}