{
  "description": null,
  "display_name": null,
  "distribution": "contrib",
  "ecosystem": "collector",
  "id": "contrib-receiver-zipkinreceiver",
  "name": "zipkinreceiver",
  "repository": "opentelemetry-collector-contrib",
  "status": {
    "class": "receiver",
    "codeowners": {
      "active": [
        "MovieStoreGuy",
        "andrzej-stencel",
        "crobert-1"
      ]
    },
    "distributions": [
      "contrib",
      "core",
      "k8s"
    ],
    "stability": {
      "beta": [
        "traces"
      ]
    }
  },
  "type": "receiver"
}